MANIFEST.in
setup.py
resweb/__init__.py
resweb/core.py
resweb/default_settings.py
resweb/views.py
resweb.egg-info/PKG-INFO
resweb.egg-info/SOURCES.txt
resweb.egg-info/dependency_links.txt
resweb.egg-info/entry_points.txt
resweb.egg-info/requires.txt
resweb.egg-info/top_level.txt
resweb/static/idle.png
resweb/static/jquery-1.3.2.min.js
resweb/static/jquery.relatize_date.js
resweb/static/poll.png
resweb/static/ranger.js
resweb/static/reset.css
resweb/static/style.css
resweb/static/working.png
resweb/templates/delayed.mustache
resweb/templates/delayed_timestamp.mustache
resweb/templates/failed.mustache
resweb/templates/footer.mustache
resweb/templates/header.mustache
resweb/templates/overview.mustache
resweb/templates/queue.mustache
resweb/templates/queue_full.mustache
resweb/templates/queues.mustache
resweb/templates/stat.mustache
resweb/templates/stats.mustache
resweb/templates/worker.mustache
resweb/templates/workers.mustache
resweb/templates/working.mustache
resweb/templates/working_full.mustache