Metadata-Version: 1.0
Name: resweb
Version: 0.1.7
Summary: Pyres web interface
Home-page: http://github.com/Pyres/resweb
Author: Matt George
Author-email: mgeorge@gmail.com
License: MIT
Download-URL: http://pypi.python.org/packages/source/p/resweb/resweb-0.1.7.tar.gz
Platform: UNKNOWN
Classifier: Development Status :: 4 - Beta
Classifier: Environment :: Console
Classifier: Intended Audience :: Developers
Classifier: License :: OSI Approved :: MIT License
Classifier: Operating System :: OS Independent
Classifier: Programming Language :: Python
